chainchat/__init__.py
chainchat/attachment.py
chainchat/cache.py
chainchat/chat.py
chainchat/cli.py
chainchat/conversation.py
chainchat/finder.py
chainchat/loader.py
chainchat/model.py
chainchat/pipe.py
chainchat/render.py
chainchat/tool.py
chainchat/trace.py
chainchat-0.1a2.dist-info/METADATA
chainchat-0.1a2.dist-info/WHEEL
chainchat-0.1a2.dist-info/entry_points.txt
chainchat-0.1a2.dist-info/licenses/LICENSE
chainchat-0.1a2.dist-info/RECORD
