Metadata-Version: 2.3
Name: chainchat
Version: 0.1a2
Summary: Chat with LangChain LLM models, with tool calling and multimodal support
Author-email: Andrew Wason <rectalogic@rectalogic.com>
Classifier: License :: OSI Approved :: GNU Affero General Public License v3 or later (AGPLv3+)
Requires-Python: >=3.12
Requires-Dist: click~=8.1.7
Requires-Dist: httpx~=0.27.2
Requires-Dist: langchain-core~=0.3.13
Requires-Dist: langgraph-checkpoint-sqlite~=2.0.1
Requires-Dist: langgraph~=0.2.39
Requires-Dist: platformdirs~=4.3.6
Requires-Dist: pydanclick~=0.3.0
Requires-Dist: python-dotenv~=1.0.1
Requires-Dist: pyyaml~=6.0.2
Requires-Dist: rich~=13.9.3
Provides-Extra: anthropic
Requires-Dist: langchain-anthropic~=0.2.4; extra == 'anthropic'
Provides-Extra: google
Requires-Dist: langchain-google-genai~=2.0.4; extra == 'google'
Provides-Extra: groq
Requires-Dist: langchain-groq~=0.2.1; extra == 'groq'
Provides-Extra: huggingface
Requires-Dist: langchain-huggingface~=0.1.2; extra == 'huggingface'
Provides-Extra: openai
Requires-Dist: langchain-openai~=0.2.5; extra == 'openai'
Provides-Extra: tools
Requires-Dist: langchain-community~=0.3.5; extra == 'tools'
